openwebuihelper/__init__.py
openwebuihelper/call_api.py
openwebuihelper/call_api_stream.py
openwebuihelper-0.1.8.dist-info/METADATA
openwebuihelper-0.1.8.dist-info/WHEEL
openwebuihelper-0.1.8.dist-info/top_level.txt
openwebuihelper-0.1.8.dist-info/RECORD
