Metadata-Version: 2.4
Name: openwebuihelper
Version: 0.1.8
Summary: open web ui extended functionality
Author-email: heifade <heifade@126.com>
License-Expression: MIT
Project-URL: Homepage, https://github.com/heifade/openwebuihelper
Classifier: Programming Language :: Python :: 3
Classifier: Operating System :: OS Independent
Requires-Python: >=3.11
Requires-Dist: aiohttp
